meg_withings-0.4.3.data/scripts/withings
meg_withings-0.4.3.dist-info/DESCRIPTION.rst
meg_withings-0.4.3.dist-info/METADATA
meg_withings-0.4.3.dist-info/RECORD
meg_withings-0.4.3.dist-info/WHEEL
meg_withings-0.4.3.dist-info/metadata.json
meg_withings-0.4.3.dist-info/top_level.txt
meg_withings-0.4.3.dist-info/zip-safe
withings/__init__.py
