Metadata-Version: 2.0
Name: meg-withings
Version: 0.4.3
Summary: Library for the Withings API
Home-page: https://git.megsupporttools.com/misc/python-withings
Author: MEG Support Tools
Author-email: michal@megsupporttools.com
License: MIT License
Keywords: withings
Platform: UNKNOWN
Requires-Dist: pytz
Requires-Dist: requests
Requires-Dist: requests-oauth
